{".class": "MypyFile", "_fullname": "utils", "is_partial_stub_package": false, "is_stub": false, "names": {".class": "SymbolTable", "Additive": {".class": "SymbolTableNode", "kind": "Gdef", "node": {".class": "TypeInfo", "_promote": null, "abstract_attributes": [], "bases": ["builtins.object"], "declared_metaclass": null, "defn": {".class": "ClassDef", "fullname": "utils.Additive", "name": "Additive", "type_vars": []}, "flags": [], "fullname": "utils.Additive", "metaclass_type": null, "metadata": {}, "module_name": "utils", "mro": ["utils.Additive", "builtins.object"], "names": {".class": "SymbolTable", "__call__": {".class": "SymbolTableNode", "kind": "Mdef", "node": {".class": "FuncDef", "arg_kinds": [0, 0, 1, 1], "arg_names": ["self", "wav", "srate", "nbits"], "flags": [], "fullname": "utils.Additive.__call__", "name": "__call__", "type": null}}, "__init__": {".class": "SymbolTableNode", "kind": "Mdef", "node": {".class": "FuncDef", "arg_kinds": [0, 0, 1, 1], "arg_names": ["self", "noises_dir", "snr_levels", "do_IRS"], "flags": [], "fullname": "utils.Additive.__init__", "name": "__init__", "type": null}}, "addnoise_asl": {".class": "SymbolTableNode", "kind": "Mdef", "node": {".class": "FuncDef", "arg_kinds": [0, 0, 0, 0, 0, 0, 1], "arg_names": ["self", "clean", "noise", "srate", "nbits", "snr", "do_IRS"], "flags": [], "fullname": "utils.Additive.addnoise_asl", "name": "addnoise_asl", "type": null}}, "apply_IRS": {".class": "SymbolTableNode", "kind": "Mdef", "node": {".class": "FuncDef", "arg_kinds": [0, 0, 0, 0], "arg_names": ["self", "data", "srate", "nbits"], "flags": [], "fullname": "utils.Additive.apply_IRS", "name": "apply_IRS", "type": null}}, "asl_P56": {".class": "SymbolTableNode", "kind": "Mdef", "node": {".class": "FuncDef", "arg_kinds": [0, 0, 0, 0], "arg_names": ["self", "x", "srate", "nbits"], "flags": [], "fullname": "utils.Additive.asl_P56", "name": "asl_P56", "type": null}}, "bin_interp": {".class": "SymbolTableNode", "kind": "Mdef", "node": {".class": "FuncDef", "arg_kinds": [0, 0, 0, 0, 0, 0, 0], "arg_names": ["self", "upcount", "lwcount", "upthr", "lwthr", "Margin", "tol"], "flags": [], "fullname": "utils.Additive.bin_interp", "name": "bin_interp", "type": null}}, "do_IRS": {".class": "SymbolTableNode", "implicit": true, "kind": "Mdef", "node": {".class": "Var", "flags": [], "fullname": "utils.Additive.do_IRS", "name": "do_IRS", "type": null}}, "eps": {".class": "SymbolTableNode", "implicit": true, "kind": "Mdef", "node": {".class": "Var", "flags": [], "fullname": "utils.Additive.eps", "name": "eps", "type": null}}, "noises": {".class": "SymbolTableNode", "implicit": true, "kind": "Mdef", "node": {".class": "Var", "flags": [], "fullname": "utils.Additive.noises", "name": "noises", "type": null}}, "noises_dir": {".class": "SymbolTableNode", "implicit": true, "kind": "Mdef", "node": {".class": "Var", "flags": [], "fullname": "utils.Additive.noises_dir", "name": "noises_dir", "type": null}}, "snr_levels": {".class": "SymbolTableNode", "implicit": true, "kind": "Mdef", "node": {".class": "Var", "flags": [], "fullname": "utils.Additive.snr_levels", "name": "snr_levels", "type": null}}}, "tuple_type": null, "type_vars": [], "typeddict_type": null}}, "ComposeAdditive": {".class": "SymbolTableNode", "kind": "Gdef", "node": {".class": "TypeInfo", "_promote": null, "abstract_attributes": [], "bases": ["builtins.object"], "declared_metaclass": null, "defn": {".class": "ClassDef", "fullname": "utils.ComposeAdditive", "name": "ComposeAdditive", "type_vars": []}, "flags": [], "fullname": "utils.ComposeAdditive", "metaclass_type": null, "metadata": {}, "module_name": "utils", "mro": ["utils.ComposeAdditive", "builtins.object"], "names": {".class": "SymbolTable", "__call__": {".class": "SymbolTableNode", "kind": "Mdef", "node": {".class": "FuncDef", "arg_kinds": [0, 0], "arg_names": ["self", "x"], "flags": [], "fullname": "utils.ComposeAdditive.__call__", "name": "__call__", "type": null}}, "__init__": {".class": "SymbolTableNode", "kind": "Mdef", "node": {".class": "FuncDef", "arg_kinds": [0, 0], "arg_names": ["self", "additive"], "flags": [], "fullname": "utils.ComposeAdditive.__init__", "name": "__init__", "type": null}}, "additive": {".class": "SymbolTableNode", "implicit": true, "kind": "Mdef", "node": {".class": "Var", "flags": [], "fullname": "utils.ComposeAdditive.additive", "name": "additive", "type": null}}}, "tuple_type": null, "type_vars": [], "typeddict_type": null}}, "CompositeEval": {".class": "SymbolTableNode", "kind": "Gdef", "node": {".class": "FuncDef", "arg_kinds": [0, 0, 1], "arg_names": ["ref_wav", "deg_wav", "log_all"], "flags": [], "fullname": "utils.CompositeEval", "name": "CompositeEval", "type": null}}, "F": {".class": "SymbolTableNode", "cross_ref": "torch.nn.functional", "kind": "Gdef"}, "PESQ": {".class": "SymbolTableNode", "kind": "Gdef", "node": {".class": "FuncDef", "arg_kinds": [0, 0], "arg_names": ["ref_wav", "deg_wav"], "flags": [], "fullname": "utils.PESQ", "name": "PESQ", "type": null}}, "PIPE": {".class": "SymbolTableNode", "cross_ref": "subprocess.PIPE", "kind": "Gdef"}, "SSNR": {".class": "SymbolTableNode", "kind": "Gdef", "node": {".class": "FuncDef", "arg_kinds": [0, 0, 1, 1], "arg_names": ["ref_wav", "deg_wav", "srate", "eps"], "flags": [], "fullname": "utils.SSNR", "name": "SSNR", "type": null}}, "__doc__": {".class": "SymbolTableNode", "kind": "Gdef", "node": {".class": "Var", "flags": ["is_ready"], "fullname": "utils.__doc__", "name": "__doc__", "type": "builtins.str"}}, "__file__": {".class": "SymbolTableNode", "kind": "Gdef", "node": {".class": "Var", "flags": ["is_ready"], "fullname": "utils.__file__", "name": "__file__", "type": "builtins.str"}}, "__name__": {".class": "SymbolTableNode", "kind": "Gdef", "node": {".class": "Var", "flags": ["is_ready"], "fullname": "utils.__name__", "name": "__name__", "type": "builtins.str"}}, "__package__": {".class": "SymbolTableNode", "kind": "Gdef", "node": {".class": "Var", "flags": ["is_ready"], "fullname": "utils.__package__", "name": "__package__", "type": "builtins.str"}}, "composite_helper": {".class": "SymbolTableNode", "kind": "Gdef", "node": {".class": "FuncDef", "arg_kinds": [0], "arg_names": ["args"], "flags": [], "fullname": "utils.composite_helper", "name": "composite_helper", "type": null}}, "denormalize_wave_minmax": {".class": "SymbolTableNode", "kind": "Gdef", "node": {".class": "FuncDef", "arg_kinds": [0], "arg_names": ["x"], "flags": [], "fullname": "utils.denormalize_wave_minmax", "name": "denormalize_wave_minmax", "type": null}}, "eval_composite": {".class": "SymbolTableNode", "kind": "Gdef", "node": {".class": "FuncDef", "arg_kinds": [0, 0, 1], "arg_names": ["clean_utt", "Genh_utt", "noisy_utt"], "flags": [], "fullname": "utils.eval_composite", "name": "eval_composite", "type": null}}, "glob": {".class": "SymbolTableNode", "cross_ref": "glob", "kind": "Gdef"}, "lfilter": {".class": "SymbolTableNode", "kind": "Gdef", "node": {".class": "Var", "flags": ["is_suppressed_import", "is_ready"], "fullname": "utils.lfilter", "name": "lfilter", "type": {".class": "AnyType", "missing_import_name": "utils.lfilter", "source_any": null, "type_of_any": 3}}}, "librosa": {".class": "SymbolTableNode", "kind": "Gdef", "node": {".class": "Var", "flags": ["is_suppressed_import", "is_ready"], "fullname": "utils.librosa", "name": "librosa", "type": {".class": "AnyType", "missing_import_name": "utils.librosa", "source_any": null, "type_of_any": 3}}}, "llr": {".class": "SymbolTableNode", "kind": "Gdef", "node": {".class": "FuncDef", "arg_kinds": [0, 0, 0], "arg_names": ["ref_wav", "deg_wav", "srate"], "flags": [], "fullname": "utils.llr", "name": "llr", "type": null}}, "lpcoeff": {".class": "SymbolTableNode", "kind": "Gdef", "node": {".class": "FuncDef", "arg_kinds": [0, 0], "arg_names": ["speech_frame", "model_order"], "flags": [], "fullname": "utils.lpcoeff", "name": "lpcoeff", "type": null}}, "make_divN": {".class": "SymbolTableNode", "kind": "Gdef", "node": {".class": "FuncDef", "arg_kinds": [0, 0, 1], "arg_names": ["tensor", "N", "method"], "flags": [], "fullname": "utils.make_divN", "name": "make_divN", "type": null}}, "np": {".class": "SymbolTableNode", "cross_ref": "numpy", "kind": "Gdef"}, "os": {".class": "SymbolTableNode", "cross_ref": "os", "kind": "Gdef"}, "re": {".class": "SymbolTableNode", "cross_ref": "re", "kind": "Gdef"}, "run": {".class": "SymbolTableNode", "cross_ref": "subprocess.run", "kind": "Gdef"}, "sf": {".class": "SymbolTableNode", "kind": "Gdef", "node": {".class": "Var", "flags": ["is_suppressed_import", "is_ready"], "fullname": "utils.sf", "name": "sf", "type": {".class": "AnyType", "missing_import_name": "utils.sf", "source_any": null, "type_of_any": 3}}}, "tempfile": {".class": "SymbolTableNode", "cross_ref": "tempfile", "kind": "Gdef"}, "toeplitz": {".class": "SymbolTableNode", "kind": "Gdef", "node": {".class": "Var", "flags": ["is_suppressed_import", "is_ready"], "fullname": "utils.toeplitz", "name": "toeplitz", "type": {".class": "AnyType", "missing_import_name": "utils.toeplitz", "source_any": null, "type_of_any": 3}}}, "torch": {".class": "SymbolTableNode", "cross_ref": "torch", "kind": "Gdef"}, "uttname2spkid": {".class": "SymbolTableNode", "kind": "Gdef", "node": {".class": "FuncDef", "arg_kinds": [0], "arg_names": ["uttname"], "flags": [], "fullname": "utils.uttname2spkid", "name": "uttname2spkid", "type": null}}, "wss": {".class": "SymbolTableNode", "kind": "Gdef", "node": {".class": "FuncDef", "arg_kinds": [0, 0, 0], "arg_names": ["ref_wav", "deg_wav", "srate"], "flags": [], "fullname": "utils.wss", "name": "wss", "type": null}}}, "path": "utils.py"}